{
    "success": [{
            "id": 886,
            "name": "   tp-6",
            "project_type": " ",
            "status": 0,
            "view_state": "50",
            "project_stage": null,
            "enabled": 1,
            "description": "",
            "sub_project": false
        },
        {
            "id": 887,
            "name": "  ty-2",
            "project_type": "   Design",
            "status": 0,
            "view_state": "50",
            "project_stage": "in progress",
            "enabled": 1,
            "description": "test",
            "sub_project": false
        },
        {
            "id": 838,
            "name": " SCH Test 1",
            "project_type": "Design",
            "status": 0,
            "view_state": "50",
            "project_stage": null,
            "enabled": 1,
            "description": "",
            "sub_project": false
        },
        {
            "id": 728,
            "name": "10000_tasks",
            "project_type": "Design",
            "status": 0,
            "view_state": "50",
            "project_stage": null,
            "enabled": 1,
            "description": "",
            "sub_project": false
        },
        {
            "id": 916,
            "name": "10000_tasks_Sub1",
            "project_type": "Learning and Development",
            "status": 0,
            "view_state": "50",
            "project_stage": null,
            "enabled": 1,
            "description": "",
            "sub_project": true,
            "parent_id": 728
        },
        {
            "id": 569,
            "name": "15th July Test",
            "project_type": "Design",
            "status": 0,
            "view_state": "50",
            "project_stage": null,
            "enabled": 1,
            "description": "",
            "sub_project": false
        },
        {
            "id": 200,
            "name": "16May-JA",
            "project_type": "Design",
            "status": 0,
            "view_state": "50",
            "project_stage": null,
            "enabled": 1,
            "description": "",
            "sub_project": false
        },
        {
            "id": 105,
            "name": "22nd April QA",
            "project_type": "Design",
            "status": 0,
            "view_state": "50",
            "project_stage": null,
            "enabled": 1,
            "description": "",
            "sub_project": false
        },
        {
            "id": 108,
            "name": "23rd April Nan",
            "project_type": "Design",
            "status": 0,
            "view_state": "50",
            "project_stage": null,
            "enabled": 1,
            "description": "",
            "sub_project": false
        },
        {
            "id": 129,
            "name": "26th AprilTest",
            "project_type": "Design",
            "status": 0,
            "view_state": "50",
            "project_stage": null,
            "enabled": 1,
            "description": "",
            "sub_project": false
        },
        {
            "id": 482,
            "name": "27thJune Test",
            "project_type": "Design",
            "status": 0,
            "view_state": "50",
            "project_stage": null,
            "enabled": 1,
            "description": "",
            "sub_project": false
        },
        {
            "id": 137,
            "name": "29th Apr",
            "project_type": "Design",
            "status": 0,
            "view_state": "50",
            "project_stage": null,
            "enabled": 1,
            "description": "",
            "sub_project": false
        },
        {
            "id": 171,
            "name": "aaa",
            "project_type": "Learning and Development",
            "status": 0,
            "view_state": "50",
            "project_stage": null,
            "enabled": 1,
            "description": "ababdhadha<iframe id=\"editorembed\" tabindex=\"-1\" style=\"position: absolute; width: 0px; height: 0px; border: none; left: -1000px; top: -1000px;\"></iframe>",
            "sub_project": false
        },
        {
            "id": 606,
            "name": "Activityidcheck",
            "project_type": "Design",
            "status": 0,
            "view_state": "50",
            "project_stage": null,
            "enabled": 1,
            "description": "",
            "sub_project": false
        },
        {
            "id": 918,
            "name": "ActivitySlider",
            "project_type": "Design",
            "status": 0,
            "view_state": "50",
            "project_stage": null,
            "enabled": 1,
            "description": "",
            "sub_project": false
        },
        {
            "id": 745,
            "name": "App Loading",
            "project_type": "Design",
            "status": 0,
            "view_state": "50",
            "project_stage": null,
            "enabled": 1,
            "description": "",
            "sub_project": false
        },
        {
            "id": 110,
            "name": "Apr 24-QA",
            "project_type": "Design",
            "status": 0,
            "view_state": "50",
            "project_stage": null,
            "enabled": 1,
            "description": "",
            "sub_project": false
        },
        {
            "id": 111,
            "name": "APR 24-QA2",
            "project_type": "Design",
            "status": 0,
            "view_state": "50",
            "project_stage": null,
            "enabled": 1,
            "description": "",
            "sub_project": false
        },
        {
            "id": 131,
            "name": "APR 26-QA",
            "project_type": "Design",
            "status": 0,
            "view_state": "50",
            "project_stage": null,
            "enabled": 1,
            "description": "<p>QA</p>",
            "sub_project": false
        },
        {
            "id": 134,
            "name": "Apr 29-QA",
            "project_type": "Design",
            "status": 0,
            "view_state": "50",
            "project_stage": null,
            "enabled": 1,
            "description": "<p>QA</p>",
            "sub_project": false
        },
        {
            "id": 133,
            "name": "APR-29",
            "project_type": "Design",
            "status": 0,
            "view_state": "50",
            "project_stage": null,
            "enabled": 1,
            "description": "<p>QA</p>",
            "sub_project": false
        },
        {
            "id": 76,
            "name": "April12QA",
            "project_type": "Design",
            "status": 0,
            "view_state": "50",
            "project_stage": null,
            "enabled": 1,
            "description": "<p>QA</p>",
            "sub_project": false
        },
        {
            "id": 80,
            "name": "April13QA",
            "project_type": "Design",
            "status": 0,
            "view_state": "50",
            "project_stage": null,
            "enabled": 1,
            "description": "<p>QA</p>",
            "sub_project": false
        },
        {
            "id": 106,
            "name": "April23_QA",
            "project_type": "Design",
            "status": 0,
            "view_state": "50",
            "project_stage": null,
            "enabled": 1,
            "description": "<p>QA</p>",
            "sub_project": false
        },
        {
            "id": 109,
            "name": "April24_QA",
            "project_type": "Design",
            "status": 0,
            "view_state": "50",
            "project_stage": null,
            "enabled": 1,
            "description": "<p>QA</p>",
            "sub_project": false
        },
        {
            "id": 130,
            "name": "April26_QA",
            "project_type": "Design",
            "status": 0,
            "view_state": "50",
            "project_stage": null,
            "enabled": 1,
            "description": "<p>QA</p>",
            "sub_project": false
        },
        {
            "id": 132,
            "name": "April29_QA",
            "project_type": "Design",
            "status": 0,
            "view_state": "50",
            "project_stage": null,
            "enabled": 1,
            "description": "<p>QA</p>",
            "sub_project": false
        },
        {
            "id": 144,
            "name": "April30_QA",
            "project_type": "Design",
            "status": 0,
            "view_state": "50",
            "project_stage": null,
            "enabled": 1,
            "description": "<p>QA</p>",
            "sub_project": false
        },
        {
            "id": 893,
            "name": "assigneecheck",
            "project_type": "Design",
            "status": 0,
            "view_state": "50",
            "project_stage": null,
            "enabled": 1,
            "description": "",
            "sub_project": false
        },
        {
            "id": 744,
            "name": "Aug 9-QA",
            "project_type": "Design",
            "status": 0,
            "view_state": "50",
            "project_stage": null,
            "enabled": 1,
            "description": "<p>QA</p>",
            "sub_project": false
        },
        {
            "id": 751,
            "name": "aug 9th-QA",
            "project_type": "Design",
            "status": 0,
            "view_state": "50",
            "project_stage": null,
            "enabled": 1,
            "description": "<p>QA</p>",
            "sub_project": false
        },
        {
            "id": 748,
            "name": "Aug12_QA",
            "project_type": "Design",
            "status": 0,
            "view_state": "50",
            "project_stage": null,
            "enabled": 1,
            "description": "<p>QA</p>",
            "sub_project": false
        },
        {
            "id": 343,
            "name": "aut123",
            "project_type": "Design",
            "status": 0,
            "view_state": "50",
            "project_stage": null,
            "enabled": 1,
            "description": "",
            "sub_project": false
        },
        {
            "id": 272,
            "name": "auto-1",
            "project_type": "Design",
            "status": 0,
            "view_state": "50",
            "project_stage": null,
            "enabled": 1,
            "description": "",
            "sub_project": false
        },
        {
            "id": 275,
            "name": "auto-2",
            "project_type": "Design",
            "status": 0,
            "view_state": "50",
            "project_stage": null,
            "enabled": 1,
            "description": "",
            "sub_project": false
        },
        {
            "id": 301,
            "name": "auto-3",
            "project_type": "Design",
            "status": 0,
            "view_state": "50",
            "project_stage": null,
            "enabled": 1,
            "description": "",
            "sub_project": false
        },
        {
            "id": 193,
            "name": "Automation123",
            "project_type": "Design",
            "status": 0,
            "view_state": "50",
            "project_stage": null,
            "enabled": 1,
            "description": "",
            "sub_project": false
        },
        {
            "id": 547,
            "name": "Balaji_Test_Construct ",
            "project_type": "Residential Building",
            "status": 0,
            "view_state": "50",
            "project_stage": null,
            "enabled": 1,
            "description": "<p>Residential Building - Consists of two towers of 15 Floors Each</p>",
            "sub_project": false
        },
        {
            "id": 11,
            "name": "Budgeting API QA",
            "project_type": "Design",
            "status": 0,
            "view_state": "50",
            "project_stage": null,
            "enabled": 1,
            "description": "",
            "sub_project": false
        },
        {
            "id": 9,
            "name": "Budgeting QA",
            "project_type": "Learning and Development",
            "status": 0,
            "view_state": "50",
            "project_stage": "Initiated",
            "enabled": 1,
            "description": "<p>This is the theodolite labeling project. We have to put Ballast first.</p><p><br></p><p>Regards</p><p>Prashant&nbsp;</p>",
            "sub_project": false
        },
        {
            "id": 70,
            "name": "budget_check",
            "project_type": "Design",
            "status": 0,
            "view_state": "50",
            "project_stage": null,
            "enabled": 1,
            "description": "<p>QA</p>",
            "sub_project": false
        },
        {
            "id": 721,
            "name": "bulkupdatecheck",
            "project_type": "Design",
            "status": 0,
            "view_state": "50",
            "project_stage": null,
            "enabled": 1,
            "description": "",
            "sub_project": false
        },
        {
            "id": 770,
            "name": "CDF STG 08|13",
            "project_type": "Design",
            "status": 0,
            "view_state": "50",
            "project_stage": null,
            "enabled": 1,
            "description": "",
            "sub_project": false
        },
        {
            "id": 27,
            "name": "Chinmay Test Project ",
            "project_type": "Design",
            "status": 0,
            "view_state": "50",
            "project_stage": null,
            "enabled": 1,
            "description": "",
            "sub_project": false
        },
        {
            "id": 684,
            "name": "Construct Drawing - STG QA",
            "project_type": "Design",
            "status": 0,
            "view_state": "50",
            "project_stage": null,
            "enabled": 1,
            "description": "",
            "sub_project": false
        },
        {
            "id": 21,
            "name": "Construct_Test",
            "project_type": "Design",
            "status": 0,
            "view_state": "50",
            "project_stage": null,
            "enabled": 1,
            "description": "",
            "sub_project": false
        },
        {
            "id": 218,
            "name": "Construct_Test123",
            "project_type": "Design",
            "status": 0,
            "view_state": "50",
            "project_stage": null,
            "enabled": 1,
            "description": "",
            "sub_project": false
        },
        {
            "id": 160,
            "name": "Costing/Budgeting API Automation",
            "project_type": "Design",
            "status": 0,
            "view_state": "50",
            "project_stage": null,
            "enabled": 1,
            "description": "",
            "sub_project": false
        },
        {
            "id": 357,
            "name": "cy-automation-1",
            "project_type": "Design",
            "status": 0,
            "view_state": "50",
            "project_stage": null,
            "enabled": 1,
            "description": "",
            "sub_project": false
        },
        {
            "id": 228,
            "name": "web-automation-1",
            "project_type": "Design",
            "status": 0,
            "view_state": "50",
            "project_stage": null,
            "enabled": 1,
            "description": "",
            "sub_project": false
        }
    ],
    "total_projects": 300
}
